{
    "state": "success",
    "message": "成功",
    "data": {
        "site_hot": [
            {
                "id": "1",
                "sid": "1",
                "name": "新浪",
                "description": "新闻资讯",
                "note": "",
                "weburl": "http://www.sina.com.cn/",
                "moburl": "http://sina.cn/",
                "add_count": "3991",
                "logo": "uploads/201310/5267999d7e857.png",
                "click_count": "3671",
                "show_is": "Y",
                "sort_order": "5",
                "create_time": "1382496400",
                "start_time": "1383580800",
                "expired_time": "1388505600"
            },
            {
                "id": "2",
                "sid": "1",
                "name": "搜狐",
                "description": "新闻资讯",
                "note": "",
                "weburl": "http://www.sohu.com/",
                "moburl": "http://m.sohu.com/",
                "add_count": "5048",
                "logo": "uploads/201311/52789b973421c.png",
                "click_count": "4417",
                "show_is": "Y",
                "sort_order": "6",
                "create_time": "1382496400",
                "start_time": "1383580800",
                "expired_time": "1386259200"
            },
            {
                "id": "9",
                "sid": "1",
                "name": "网易",
                "description": "新闻资讯",
                "note": "",
                "weburl": "http://www.163.com/",
                "moburl": "http://3g.163.com/",
                "add_count": "5597",
                "logo": "uploads/201311/52789a352c7da.png",
                "click_count": "4527",
                "show_is": "Y",
                "sort_order": "7",
                "create_time": "1382496400",
                "start_time": "1383580800",
                "expired_time": "1383667200"
            },
            {
                "id": "3",
                "sid": "1",
                "name": "腾讯",
                "description": "新闻资讯",
                "note": "",
                "weburl": "http://www.qq.com/",
                "moburl": "http://3gqq.qq.com/",
                "add_count": "4269",
                "logo": "uploads/201311/52789b7ceb4a5.png",
                "click_count": "4872",
                "show_is": "Y",
                "sort_order": "8",
                "create_time": "1382496400",
                "start_time": "1383580800",
                "expired_time": "1383667200"
            },
            {
                "id": "34",
                "sid": "4",
                "name": "淘宝",
                "description": "商城",
                "note": "",
                "weburl": "http://www.taobao.com/",
                "moburl": "http://m.taobao.com/",
                "add_count": "5636",
                "logo": "uploads/201311/5278876806b5d.png",
                "click_count": "3093",
                "show_is": "Y",
                "sort_order": "9",
                "create_time": "1382496400",
                "start_time": "1383580800",
                "expired_time": "1383667200"
            },
            {
                "id": "217",
                "sid": "22",
                "name": "百度",
                "description": "搜索引擎",
                "note": "",
                "weburl": "http://www.baidu.com/",
                "moburl": "http://m.baidu.com/",
                "add_count": "5980",
                "logo": "uploads/201311/527884c4c524b.png",
                "click_count": "5134",
                "show_is": "Y",
                "sort_order": "10",
                "create_time": "1382680387",
                "start_time": "1383580800",
                "expired_time": "1388505600"
            },
            {
                "id": "300",
                "sid": "4",
                "name": "易迅",
                "description": "",
                "note": "",
                "weburl": "http://www.yixun.com/",
                "moburl": "http://m.yixun.com/t/#",
                "add_count": "0",
                "logo": "uploads/201402/530d8d30c5b4c.jpg",
                "click_count": "3308",
                "show_is": "Y",
                "sort_order": "11",
                "create_time": "1392712402",
                "start_time": "1392652800",
                "expired_time": "1424275200"
            },
            {
                "id": "26",
                "sid": "4",
                "name": "京东",
                "description": "商城",
                "note": "",
                "weburl": "http://www.jd.com/",
                "moburl": "http://m.jd.com/",
                "add_count": "5539",
                "logo": "uploads/201311/52788dee6791a.png",
                "click_count": "3039",
                "show_is": "Y",
                "sort_order": "12",
                "create_time": "1382496400",
                "start_time": "1392652800",
                "expired_time": "1424275200"
            },
            {
                "id": "42",
                "sid": "5",
                "name": "优酷",
                "description": "视频",
                "note": "",
                "weburl": "http://www.youku.com/",
                "moburl": "http://m.youku.com/",
                "add_count": "4983",
                "logo": "uploads/201311/527886bf2adf3.png",
                "click_count": "5261",
                "show_is": "Y",
                "sort_order": "13",
                "create_time": "1382496400",
                "start_time": "1383580800",
                "expired_time": "1383667200"
            },
            {
                "id": "116",
                "sid": "14",
                "name": "58",
                "description": "生活(同城)",
                "note": "",
                "weburl": "http://www.58.com/",
                "moburl": "http://wap.58.com/",
                "add_count": "5565",
                "logo": "uploads/201310/5268e21680872.png",
                "click_count": "5884",
                "show_is": "Y",
                "sort_order": "14",
                "create_time": "1382496400",
                "start_time": "1392652800",
                "expired_time": "1424275200"
            },
            {
                "id": "43",
                "sid": "5",
                "name": "凤凰",
                "description": "视频",
                "note": "",
                "weburl": "http://v.ifeng.com/",
                "moburl": "http://apps.ifeng.com/",
                "add_count": "3948",
                "logo": "uploads/201311/5278868054f8a.png",
                "click_count": "5423",
                "show_is": "Y",
                "sort_order": "15",
                "create_time": "1382496400",
                "start_time": "1392652800",
                "expired_time": "1424275200"
            },
            {
                "id": "194",
                "sid": "20",
                "name": "和讯",
                "description": "财经",
                "note": "",
                "weburl": "http://www.hexun.com/",
                "moburl": "http://m.hexun.com/",
                "add_count": "5487",
                "logo": "uploads/201310/5268c4948fc43.png",
                "click_count": "5373",
                "show_is": "Y",
                "sort_order": "16",
                "create_time": "1382593724",
                "start_time": "1392652800",
                "expired_time": "1425484800"
            }
        ],
        "site_class": {
            "9": {
                "id": "9",
                "name": "邮箱",
                "data": [
                    {
                        "id": "64",
                        "name": "163",
                        "weburl": "http://mail.163.com/",
                        "moburl": "http://m.mail.163.com/",
                        "logo": "uploads/201310/5269db11992d1.png"
                    },
                    {
                        "id": "65",
                        "name": "新浪",
                        "weburl": "https://mail.sina.com.cn/",
                        "moburl": "https://mail.sina.com.cn/mobile/index.php?vt=3",
                        "logo": "uploads/201310/5269db04bbf6a.png"
                    },
                    {
                        "id": "66",
                        "name": "QQ",
                        "weburl": "http://mail.qq.com/",
                        "moburl": "https://w.mail.qq.com/cgi-bin/loginpage",
                        "logo": "uploads/201310/5269daeddf63a.png"
                    },
                    {
                        "id": "67",
                        "name": "139",
                        "weburl": "http://mail.10086.cn/",
                        "moburl": "http://wapmail.10086.cn/",
                        "logo": "uploads/201310/5269dad8311c0.png"
                    }
                ]
            },
            "15": {
                "id": "15",
                "name": "汽车",
                "data": [
                    {
                        "id": "127",
                        "name": "汽车之家",
                        "weburl": "http://www.autohome.com.cn/",
                        "moburl": "http://m.autohome.com.cn/",
                        "logo": "uploads/201310/5268e133833db.png"
                    },
                    {
                        "id": "128",
                        "name": "新浪",
                        "weburl": "http://auto.sina.com.cn/",
                        "moburl": "http://auto.sina.cn/",
                        "logo": "uploads/201310/5268e12674786.png"
                    },
                    {
                        "id": "129",
                        "name": "爱卡",
                        "weburl": "http://www.xcar.com.cn/",
                        "moburl": "http://wap.xcar.com.cn/",
                        "logo": "uploads/201310/5268e119d9ab4.png"
                    },
                    {
                        "id": "130",
                        "name": "搜狐",
                        "weburl": "http://auto.sohu.com/",
                        "moburl": "http://m.sohu.com/c/1592/",
                        "logo": "uploads/201310/5268e10d2f21d.png"
                    }
                ]
            },
            "17": {
                "id": "17",
                "name": "银行",
                "data": [
                    {
                        "id": "155",
                        "name": "工商",
                        "weburl": "http://www.icbc.com.cn/icbc/",
                        "moburl": "http://wap.icbc.com.cn/",
                        "logo": "uploads/201310/5268db9f74606.png"
                    },
                    {
                        "id": "156",
                        "name": "建设",
                        "weburl": "http://www.ccb.com/cn/home/index.html",
                        "moburl": "http://m.ccb.com/cn/mobile/index.html",
                        "logo": "uploads/201310/5268dae04d724.png"
                    },
                    {
                        "id": "157",
                        "name": "中国银行",
                        "weburl": "http://www.boc.cn/",
                        "moburl": "http://mbs.boc.cn/",
                        "logo": "uploads/201310/5268da92dc418.png"
                    },
                    {
                        "id": "158",
                        "name": "交通",
                        "weburl": "http://www.bankcomm.com/",
                        "moburl": "http://wap.95559.com.cn/",
                        "logo": "uploads/201310/5268d9bcb2a8d.png"
                    }
                ]
            },
            "18": {
                "id": "18",
                "name": "手机",
                "data": [
                    {
                        "id": "170",
                        "name": "移动",
                        "weburl": "http://www.10086.cn/gd/",
                        "moburl": "http://wap.10086.cn/error.html",
                        "logo": "uploads/201310/5268cad131e36.png"
                    },
                    {
                        "id": "171",
                        "name": "联通",
                        "weburl": "http://www.10010.com/",
                        "moburl": "http://wap.10010.com/",
                        "logo": "uploads/201310/5268cabb593b1.png"
                    },
                    {
                        "id": "172",
                        "name": "电信",
                        "weburl": "http://www.189.cn/",
                        "moburl": "http://wapzt.189.cn/provinces.do",
                        "logo": "uploads/201310/5268caa1abfef.png"
                    },
                    {
                        "id": "173",
                        "name": "中关村",
                        "weburl": "http://www.zol.com.cn/",
                        "moburl": "http://3g.zol.com.cn/",
                        "logo": "uploads/201310/5268ca8b6c8c5.png"
                    }
                ]
            },
            "22": {
                "id": "22",
                "name": "搜索引擎",
                "data": [
                    {
                        "id": "218",
                        "name": "谷歌",
                        "weburl": "http://www.google.com.hk/",
                        "moburl": "http://www.google.cn/",
                        "logo": "uploads/201311/527884b7bf893.png"
                    },
                    {
                        "id": "217",
                        "name": "百度",
                        "weburl": "http://www.baidu.com/",
                        "moburl": "http://m.baidu.com/",
                        "logo": "uploads/201311/527884c4c524b.png"
                    },
                    {
                        "id": "172",
                        "name": "电信",
                        "weburl": "http://www.189.cn/",
                        "moburl": "http://wapzt.189.cn/provinces.do",
                        "logo": "uploads/201310/5268caa1abfef.png"
                    },
                    {
                        "id": "173",
                        "name": "中关村",
                        "weburl": "http://www.zol.com.cn/",
                        "moburl": "http://3g.zol.com.cn/",
                        "logo": "uploads/201310/5268ca8b6c8c5.png"
                    }
                ]
            },
            "23": {
                "id": "23",
                "name": "休闲娱乐",
                "desp": "一次性搜索超过 30000 个应用程序",
                "data": {
                    "0": {
                        "id": "2",
                        "name": "阅读学习",
                        "data": [
                            {
                                "id": "276",
                                "name": "电子书",
                                "weburl": "http://www.wandoujia.com/tag/%E7%94%B5%E5%AD%90%E4%B9%A6",
                                "moburl": "http://www.wandoujia.com/tag/%E7%94%B5%E5%AD%90%E4%B9%A6",
                                "logo": "uploads/201402/530d8a9e2cf8b.jpg"
                            },
                            {
                                "id": "277",
                                "name": "漫画",
                                "weburl": "http://www.wandoujia.com/tag/%E6%BC%AB%E7%94%BB",
                                "moburl": "http://www.wandoujia.com/tag/%E6%BC%AB%E7%94%BB",
                                "logo": "uploads/201402/530d8a9454473.jpg"
                            },
                            {
                                "id": "278",
                                "name": "小说",
                                "weburl": "http://www.wandoujia.com/tag/%E5%B0%8F%E8%AF%B4",
                                "moburl": "http://www.wandoujia.com/tag/%E5%B0%8F%E8%AF%B4",
                                "logo": "uploads/201402/530d8d084a7c1.jpg"
                            },
                            {
                                "id": "279",
                                "name": "英语",
                                "weburl": "http://www.wandoujia.com/tag/%E8%8B%B1%E8%AF%AD",
                                "moburl": "http://www.wandoujia.com/tag/%E8%8B%B1%E8%AF%AD",
                                "logo": "uploads/201402/530d8a0adbd46.jpg"
                            }
                        ]
                    },
                    "12": {
                        "id": "38",
                        "name": "影音图像",
                        "data": [
                            {
                                "id": "280",
                                "name": "视频",
                                "weburl": "http://www.wandoujia.com/tag/%E8%A7%86%E9%A2%91",
                                "moburl": "http://www.wandoujia.com/tag/%E8%A7%86%E9%A2%91",
                                "logo": "uploads/201402/530d89f0a3244.jpg"
                            },
                            {
                                "id": "281",
                                "name": "播放器",
                                "weburl": "http://www.wandoujia.com/tag/%E6%92%AD%E6%94%BE%E5%99%A8",
                                "moburl": "http://www.wandoujia.com/tag/%E6%92%AD%E6%94%BE%E5%99%A8",
                                "logo": "uploads/201402/530d89d794dc3.jpg"
                            },
                            {
                                "id": "282",
                                "name": "音乐",
                                "weburl": "http://www.wandoujia.com/tag/%E9%9F%B3%E4%B9%90",
                                "moburl": "http://www.wandoujia.com/tag/%E9%9F%B3%E4%B9%90",
                                "logo": "uploads/201402/530d89b7470c3.jpg"
                            },
                            {
                                "id": "283",
                                "name": "相机",
                                "weburl": "http://www.wandoujia.com/tag/%E7%9B%B8%E6%9C%BA",
                                "moburl": "http://www.wandoujia.com/tag/%E7%9B%B8%E6%9C%BA",
                                "logo": "uploads/201402/530d89712b31f.jpg"
                            }
                        ]
                    }
                }
            },
            "24": {
                "id": "24",
                "name": "资讯阅读",
                "desp": "面向全球范围的华人提供最新的资讯信息",
                "data": {
                    "10": {
                        "id": "1",
                        "name": "新闻",
                        "data": [
                            {
                                "id": "4",
                                "name": "人民",
                                "weburl": "http://www.people.com.cn/",
                                "moburl": "http://m.people.cn/4g/",
                                "logo": "uploads/201311/52789b1f76ee6.png"
                            },
                            {
                                "id": "56",
                                "name": "环球",
                                "weburl": "http://www.xinjunshi.com/",
                                "moburl": "http://m.xinjunshi.com/",
                                "logo": "uploads/201310/5269deb61862d.png"
                            },
                            {
                                "id": "299",
                                "name": "中新",
                                "weburl": "http://www.chinanews.com/",
                                "moburl": "http://m.chinanews.com/c/",
                                "logo": "uploads/201402/530d8e2ec7dfb.jpg"
                            },
                            {
                                "id": "262",
                                "name": "头条",
                                "weburl": "http://www.toutiao.com/",
                                "moburl": "http://m.toutiao.com/",
                                "logo": "uploads/201402/530d8b1b73f74.jpg"
                            }
                        ]
                    },
                    "19": {
                        "id": "7",
                        "name": "军事",
                        "data": [
                            {
                                "id": "51",
                                "name": "中华",
                                "weburl": "http://military.china.com/zh_cn/",
                                "moburl": "http://3g.china.com/?vt=3",
                                "logo": "uploads/201311/5278852b8fef7.png"
                            },
                            {
                                "id": "53",
                                "name": "铁血",
                                "weburl": "http://www.tiexue.net/",
                                "moburl": "http://m.tiexue.net/3g/",
                                "logo": "uploads/201310/5269df35d559d.png"
                            },
                            {
                                "id": "263",
                                "name": "前沿",
                                "weburl": "http://www.qianyan001.com/",
                                "moburl": "http://m.qianyan001.com/",
                                "logo": "uploads/201402/530d8b0f8df3f.jpg"
                            },
                            {
                                "id": "216",
                                "name": "西陆",
                                "weburl": "http://www.xilu.com/",
                                "moburl": "http://m.xilu.com/",
                                "logo": "uploads/201310/5269d7a561ee1.png"
                            }
                        ]
                    },
                    "20": {
                        "id": "8",
                        "name": "体育",
                        "data": [
                            {
                                "id": "63",
                                "name": "NBA",
                                "weburl": "http://sports.sina.com.cn/nba/",
                                "moburl": "http://nba.sina.cn/",
                                "logo": "uploads/201310/5269dc351a51d.png"
                            },
                            {
                                "id": "60",
                                "name": "虎扑",
                                "weburl": "http://www.hupu.com/",
                                "moburl": "http://wap.hupu.com/",
                                "logo": "uploads/201310/5269dc0c5a626.png"
                            },
                            {
                                "id": "61",
                                "name": "网易",
                                "weburl": "http://sports.163.com/",
                                "moburl": "http://help.3g.163.com/p/3g.163.com/sports/",
                                "logo": "uploads/201310/5269dbfa414f1.png"
                            },
                            {
                                "id": "62",
                                "name": "直播吧",
                                "weburl": "http://www.zhibo8.cc/",
                                "moburl": "http://m.zhibo8.cc/",
                                "logo": "uploads/201310/5269dbe9c1540.png"
                            }
                        ]
                    },
                    "32": {
                        "id": "20",
                        "name": "财经",
                        "data": [
                            {
                                "id": "193",
                                "name": "新浪",
                                "weburl": "http://finance.sina.com.cn/",
                                "moburl": "http://finance.sina.cn/",
                                "logo": "uploads/201310/5268c4b7227a2.png"
                            },
                            {
                                "id": "220",
                                "name": "东方",
                                "weburl": "http://www.eastmoney.com/",
                                "moburl": "http://wap.eastmoney.com/",
                                "logo": "uploads/201311/5278849766b1a.png"
                            },
                            {
                                "id": "195",
                                "name": "大智慧",
                                "weburl": "http://www.gw.com.cn/",
                                "moburl": "http://wapgw.cn/",
                                "logo": "uploads/201310/5268c4670c3a5.png"
                            },
                            {
                                "id": "196",
                                "name": "中金",
                                "weburl": "http://www.cnfol.com/",
                                "moburl": "http://3g.cnfol.com/",
                                "logo": "uploads/201310/5268c455b679f.png"
                            }
                        ]
                    }
                }
            },
            "25": {
                "id": "25",
                "name": "社区交友",
                "desp": "",
                "data": {
                    "23": {
                        "id": "11",
                        "name": "社区",
                        "data": [
                            {
                                "id": "219",
                                "name": "百度贴吧",
                                "weburl": "http://tieba.baidu.com/",
                                "moburl": "http://tieba.baidu.com/?page=hot",
                                "logo": "uploads/201311/527884a1cf96e.png"
                            },
                            {
                                "id": "79",
                                "name": "天涯",
                                "weburl": "http://www.tianya.cn/",
                                "moburl": "http://m.tianya.cn/",
                                "logo": "uploads/201310/5269d82a8179d.png"
                            },
                            {
                                "id": "80",
                                "name": "猫扑",
                                "weburl": "http://dzh.mop.com/",
                                "moburl": "http://m.mop.com/",
                                "logo": "uploads/201310/5269d81765b41.png"
                            },
                            {
                                "id": "81",
                                "name": "新浪",
                                "weburl": "http://bbs.sina.com.cn/",
                                "moburl": "http://bbs.sina.cn/?ttp=bottomnavbbs&pos=108&vt=4",
                                "logo": "uploads/201310/5269d80ae7b60.png"
                            }
                        ]
                    },
                    "24": {
                        "id": "12",
                        "name": "社交",
                        "data": [
                            {
                                "id": "89",
                                "name": "人人",
                                "weburl": "http://www.renren.com/",
                                "moburl": "http://m.renren.com/",
                                "logo": "uploads/201310/5269d67baa868.png"
                            },
                            {
                                "id": "90",
                                "name": "开心",
                                "weburl": "http://www.kaixin001.com/",
                                "moburl": "http://m.kaixin001.com/",
                                "logo": "uploads/201310/5269d61ec8a54.png"
                            },
                            {
                                "id": "91",
                                "name": "腾讯朋友",
                                "weburl": "http://www.pengyou.com/",
                                "moburl": "http://m.pengyou.com/",
                                "logo": "uploads/201310/5269d5f49c89d.png"
                            },
                            {
                                "id": "92",
                                "name": "ChinaRen",
                                "weburl": "http://www.chinaren.com/",
                                "moburl": "http://class.chinaren.com/",
                                "logo": "uploads/201310/5269d012972fb.png"
                            }
                        ]
                    },
                    "25": {
                        "id": "13",
                        "name": "交友",
                        "data": [
                            {
                                "id": "99",
                                "name": "世纪佳缘",
                                "weburl": "http://www.jiayuan.com/",
                                "moburl": "http://m.jiayuan.com/",
                                "logo": "uploads/201310/5268e9d4900a5.png"
                            },
                            {
                                "id": "100",
                                "name": "百合",
                                "weburl": "http://www.baihe.com/",
                                "moburl": "http://m.baihe.com/",
                                "logo": "uploads/201310/5268e9c220c7f.png"
                            },
                            {
                                "id": "101",
                                "name": "珍爱",
                                "weburl": "http://www.zhenai.com/",
                                "moburl": "http://m.zhenai.com/",
                                "logo": "uploads/201310/5268e96563c3f.png"
                            },
                            {
                                "id": "102",
                                "name": "58交友",
                                "weburl": "http://jiaoyou.58.com/",
                                "moburl": "http://m.jiaoyou.58.com/",
                                "logo": "uploads/201310/5268e933cf724.png"
                            }
                        ]
                    }
                }
            },
            "26": {
                "id": "26",
                "name": "娱乐",
                "desp": "天天向上",
                "data": {
                    "7": {
                        "id": "30",
                        "name": "搞笑",
                        "data": [
                            {
                                "id": "253",
                                "name": "笑乐并排",
                                "weburl": "http://huaban.com/fm/qqxiaosi/pins/?md=qqapp",
                                "moburl": "http://huaban.com/fm/qqxiaosi/pins/?md=qqapp",
                                "logo": "uploads/201311/527c9b0a5ae67.png"
                            },
                            {
                                "id": "252",
                                "name": "捧腹网",
                                "weburl": "http://m.pengfu.com/",
                                "moburl": "http://m.pengfu.com/",
                                "logo": "uploads/201311/527c9ae556588.png"
                            },
                            {
                                "id": "251",
                                "name": "冷笑话精",
                                "weburl": "http://m.lengxiaohua.cn/touch/index",
                                "moburl": "http://m.lengxiaohua.cn/touch/index",
                                "logo": "uploads/201311/527c9ac7556ec.png"
                            },
                            {
                                "id": "250",
                                "name": "内涵段子",
                                "weburl": "http://m.toutiao.com/essay/joke/?utm_source=qq_browser",
                                "moburl": "http://m.toutiao.com/essay/joke/?utm_source=qq_browser",
                                "logo": "uploads/201311/527c9aaa26352.png"
                            }
                        ]
                    },
                    "8": {
                        "id": "32",
                        "name": "漫画",
                        "data": [
                            {
                                "id": "245",
                                "name": "海贼王",
                                "weburl": "http://mb.ac.qq.com/#!/comic/505430",
                                "moburl": "http://mb.ac.qq.com/#!/comic/505430",
                                "logo": "uploads/201311/527c996843fd2.png"
                            },
                            {
                                "id": "244",
                                "name": "火影忍者",
                                "weburl": "http://mb.ac.qq.com/#!/comic/505432",
                                "moburl": "http://mb.ac.qq.com/#!/comic/505432",
                                "logo": "uploads/201311/527c994feacb6.png"
                            },
                            {
                                "id": "243",
                                "name": "寡妇三代",
                                "weburl": "http://manhua.yicha.cn/manhua/cartoonsimple_16ae6e256318907f.html?cartoonId=16ae6e256318907f&site=2145959211&t=lw&tp=",
                                "moburl": "http://manhua.yicha.cn/manhua/cartoonsimple_16ae6e256318907f.html?cartoonId=16ae6e256318907f&site=2145959211&t=lw&tp=",
                                "logo": "uploads/201311/527c98ffb9b2b.png"
                            },
                            {
                                "id": "242",
                                "name": "邪恶漫画",
                                "weburl": "http://manhua.yicha.cn/manhua/cartoonsimple_f05145b419caec2e.html?cartoonId=f05145b419caec2e&site=2145959211&t=lw&tp=",
                                "moburl": "http://manhua.yicha.cn/manhua/cartoonsimple_f05145b419caec2e.html?cartoonId=f05145b419caec2e&site=2145959211&t=lw&tp=",
                                "logo": "uploads/201311/527c98d635dc3.png"
                            }
                        ]
                    },
                    "18": {
                        "id": "5",
                        "name": "影音",
                        "data": [
                            {
                                "id": "35",
                                "name": "爱奇艺",
                                "weburl": "http://www.iqiyi.com/",
                                "moburl": "http://m.iqiyi.com/",
                                "logo": "uploads/201311/527887411971f.png"
                            },
                            {
                                "id": "36",
                                "name": "土豆",
                                "weburl": "http://www.tudou.com/",
                                "moburl": "http://m.tudou.com/",
                                "logo": "uploads/201311/527887350f61a.png"
                            },
                            {
                                "id": "37",
                                "name": "搜狐",
                                "weburl": "http://tv.sohu.com/",
                                "moburl": "http://m.tv.sohu.com",
                                "logo": "uploads/201311/5278872134d36.png"
                            },
                            {
                                "id": "38",
                                "name": "乐视",
                                "weburl": "http://www.letv.com/",
                                "moburl": "http://m.letv.com/",
                                "logo": "uploads/201311/52788711e9076.png"
                            }
                        ]
                    },
                    "22": {
                        "id": "10",
                        "name": "音乐",
                        "data": [
                            {
                                "id": "73",
                                "name": "一听",
                                "weburl": "http://www.1ting.com/",
                                "moburl": "http://m.1ting.com/",
                                "logo": "uploads/201310/5269d94e225bf.png"
                            },
                            {
                                "id": "74",
                                "name": "酷狗",
                                "weburl": "http://www.kugou.com/1153",
                                "moburl": "http://m.kugou.com",
                                "logo": "uploads/201310/5269d927f2fae.png"
                            },
                            {
                                "id": "75",
                                "name": "QQ音乐",
                                "weburl": "http://y.qq.com/",
                                "moburl": "http://music.3g.qq.com/",
                                "logo": "uploads/201310/5269d90795a6e.png"
                            },
                            {
                                "id": "76",
                                "name": "音悦台",
                                "weburl": "http://www.yinyuetai.com/",
                                "moburl": "http://www.yinyuetai.com/apps/mobile/official",
                                "logo": "uploads/201310/5269d84f62178.png"
                            }
                        ]
                    }
                }
            },
            "27": {
                "id": "27",
                "name": "生活购物",
                "desp": "海量精品折扣 优惠折扣 全年无休",
                "data": {
                    "17": {
                        "id": "4",
                        "name": "购物",
                        "data": [
                            {
                                "id": "284",
                                "name": "特卖",
                                "weburl": "http://s.click.taobao.com/t?e=m%3D2%26s%3DOy5vwFTr%2BLscQipKwQzePCperVdZeJviEViQ0P1Vf2kguMN8XjClAvc90NJdwFFihNa%2BloB3odaIec1wWntckvv2EIZCGtmvZNFSOdUUG2uwEq4jQTyaDOo0BcZWWIRYYA%2FDpPH01wK9AmARIwX9K%2BAjBDXvuqoU47FHjfsActnIQu5PdXpojKJn5AyUbPoV",
                                "moburl": "http://s.click.taobao.com/t?e=m%3D2%26s%3DOy5vwFTr%2BLscQipKwQzePCperVdZeJviEViQ0P1Vf2kguMN8XjClAvc90NJdwFFihNa%2BloB3odaIec1wWntckvv2EIZCGtmvZNFSOdUUG2uwEq4jQTyaDOo0BcZWWIRYYA%2FDpPH01wK9AmARIwX9K%2BAjBDXvuqoU47FHjfsActnIQu5PdXpojKJn5AyUbPoV",
                                "logo": "uploads/201402/530d894476e1f.jpg"
                            },
                            {
                                "id": "285",
                                "name": "新品",
                                "weburl": "http://s.click.taobao.com/t?e=m%3D2%26s%3DwgUJfHRrZmocQipKwQzePCperVdZeJvipRe%2F8jaAHci5VBFTL4hn2dReaLtbQB%2BttTN3K9waqqj4MjSOI2O05RjLeNbPeaZb5TtazDcelbfWS2bKTkQQxr0CYBEjBf0rrZBPdiZP10sI3pH8fWQUpbHfv3%2BBYcPWXmPstG5W4bHGJe8N%2FwNpGw%3D%3D",
                                "moburl": "http://s.click.taobao.com/t?e=m%3D2%26s%3DwgUJfHRrZmocQipKwQzePCperVdZeJvipRe%2F8jaAHci5VBFTL4hn2dReaLtbQB%2BttTN3K9waqqj4MjSOI2O05RjLeNbPeaZb5TtazDcelbfWS2bKTkQQxr0CYBEjBf0rrZBPdiZP10sI3pH8fWQUpbHfv3%2BBYcPWXmPstG5W4bHGJe8N%2FwNpGw%3D%3D",
                                "logo": "uploads/201402/530d893cd145b.jpg"
                            },
                            {
                                "id": "286",
                                "name": "热卖",
                                "weburl": "http://s.click.taobao.com/t?e=m%3D2%26s%3DOF9Nv40LthgcQipKwQzePCperVdZeJvipRe%2F8jaAHci5VBFTL4hn2dReaLtbQB%2BtP5bxJy%2F%2Fu7j4MjSOI2O05RjLeNbPeaZbcLPlJHjS2juVvXoofVq6PL0CYBEjBf0rPeaJrvmJUgCIGrHgCgZNHKist33dC4JQxg5p7bh%2BFbQ%3D",
                                "moburl": "http://m.taobao.com/",
                                "logo": "uploads/201402/530d893534ae2.jpg"
                            },
                            {
                                "id": "287",
                                "name": "清仓",
                                "weburl": "http://s.click.taobao.com/t?e=m%3D2%26s%3DcikLK2J%2BRZEcQipKwQzePCperVdZeJvipRe%2F8jaAHci5VBFTL4hn2RHkw8kSOp3lHGUKWrwhgPn4MjSOI2O05RjLeNbPeaZboNFBbCRro%2Fn2oW%2FoNuzPvb0CYBEjBf0rJWM3CggMZwCyOA9cSz2R4348ZegCJ4jaSRoZW2nfVFs%3D",
                                "moburl": "http://s.click.taobao.com/t?e=m%3D2%26s%3DcikLK2J%2BRZEcQipKwQzePCperVdZeJvipRe%2F8jaAHci5VBFTL4hn2RHkw8kSOp3lHGUKWrwhgPn4MjSOI2O05RjLeNbPeaZboNFBbCRro%2Fn2oW%2FoNuzPvb0CYBEjBf0rJWM3CggMZwCyOA9cSz2R4348ZegCJ4jaSRoZW2nfVFs%3D",
                                "logo": "uploads/201402/530d892bc14e4.jpg"
                            }
                        ]
                    },
                    "26": {
                        "id": "14",
                        "name": "服装",
                        "data": [
                            {
                                "id": "288",
                                "name": "女装",
                                "weburl": "http://s.click.taobao.com/t?e=m%3D2%26s%3D8TYN6jxdY7ccQipKwQzePCperVdZeJvipRe%2F8jaAHci5VBFTL4hn2TEwrbK0twasy4nB2TbTLwL4MjSOI2O05RjLeNbPeaZbygkZuWGtuPpCM%2FxycLXdNr0CYBEjBf0rLxRPKN2FDAck%2FCKKDVvEs%2FIcvT56TvpnXnJzxlaAQLxKqktrJqjn6EZAdEvZRH5vxg5p7bh%2BFbQ%3D",
                                "moburl": "http://m.tmall.com/",
                                "logo": "uploads/201402/530d892476f6f.jpg"
                            },
                            {
                                "id": "289",
                                "name": "男装",
                                "weburl": "http://s.click.taobao.com/t?e=m%3D2%26s%3D7qf6cdeGlqkcQipKwQzePCperVdZeJvipRe%2F8jaAHci5VBFTL4hn2aTlbBMJV5hxwSB8%2FImevID4MjSOI2O05RjLeNbPeaZb4KlPST9oC9m5UF08r%2BjSmL0CYBEjBf0rDqiH1eKZ%2BMpPnXgIvLorkxb3kPS3do6KXaMPXfzA%2Fl0%3D",
                                "moburl": "http://s.click.taobao.com/t?e=m%3D2%26s%3D7qf6cdeGlqkcQipKwQzePCperVdZeJvipRe%2F8jaAHci5VBFTL4hn2aTlbBMJV5hxwSB8%2FImevID4MjSOI2O05RjLeNbPeaZb4KlPST9oC9m5UF08r%2BjSmL0CYBEjBf0rDqiH1eKZ%2BMpPnXgIvLorkxb3kPS3do6KXaMPXfzA%2Fl0%3D",
                                "logo": "uploads/201402/530d891d4a9d6.jpg"
                            },
                            {
                                "id": "290",
                                "name": "户外",
                                "weburl": "http://s.click.taobao.com/t?e=m%3D2%26s%3DRFYxnot3s%2FEcQipKwQzePCperVdZeJvipRe%2F8jaAHci5VBFTL4hn2dVil4WBwdz62Y%2Bdtp35Zpr4MjSOI2O05RjLeNbPeaZbpCRVvOOdhLT7eF5MuJaQ3L0CYBEjBf0rgQbd8LEdAvGIGrHgCgZNHKist33dC4JQxg5p7bh%2BFbQ%3D",
                                "moburl": "http://s.click.taobao.com/t?e=m%3D2%26s%3DRFYxnot3s%2FEcQipKwQzePCperVdZeJvipRe%2F8jaAHci5VBFTL4hn2dVil4WBwdz62Y%2Bdtp35Zpr4MjSOI2O05RjLeNbPeaZbpCRVvOOdhLT7eF5MuJaQ3L0CYBEjBf0rgQbd8LEdAvGIGrHgCgZNHKist33dC4JQxg5p7bh%2BFbQ%3D",
                                "logo": "uploads/201402/530d890eb9adf.jpg"
                            },
                            {
                                "id": "291",
                                "name": "品牌",
                                "weburl": "http://s.click.taobao.com/t?e=m%3D2%26s%3DOF9Nv40LthgcQipKwQzePCperVdZeJvipRe%2F8jaAHci5VBFTL4hn2dReaLtbQB%2BtP5bxJy%2F%2Fu7j4MjSOI2O05RjLeNbPeaZbcLPlJHjS2juVvXoofVq6PL0CYBEjBf0rPeaJrvmJUgCIGrHgCgZNHKist33dC4JQxg5p7bh%2BFbQ%3D",
                                "moburl": "http://m.tmall.com/",
                                "logo": "uploads/201402/530d8905387c0.jpg"
                            }
                        ]
                    },
                    "28": {
                        "id": "16",
                        "name": "数码",
                        "data": [
                            {
                                "id": "292",
                                "name": "移动电源",
                                "weburl": "http://redirect.simba.taobao.com/rd?w=unionnojs&f=http%3A%2F%2Fre.taobao.com%2Feauction%3Fe%3DhBaeWzwghOcjmraEDZVrLhsGfTffQhjQ%252Fu2ibf7AQV2LltG5xFicOSZqewpHPyZz7AXbFc1ykcSNNjMGIU4MqTM%252FQp3P6l3DQjRWJmbfy6OB3ujUJI0OeA%253D%253D%26ptype%3D100010&k=e2e107a2b72ca1b1&c=un&b=alimm_0&p=mm_42564825_4062167_17414952",
                                "moburl": "http://redirect.simba.taobao.com/rd?w=unionnojs&f=http%3A%2F%2Fre.taobao.com%2Feauction%3Fe%3DhBaeWzwghOcjmraEDZVrLhsGfTffQhjQ%252Fu2ibf7AQV2LltG5xFicOSZqewpHPyZz7AXbFc1ykcSNNjMGIU4MqTM%252FQp3P6l3DQjRWJmbfy6OB3ujUJI0OeA%253D%253D%26ptype%3D100010&k=e2e107a2b72ca1b1&c=un&b=alimm_0&p=mm_42564825_4062167_17414952",
                                "logo": "uploads/201402/530170c997d3a.jpg"
                            },
                            {
                                "id": "293",
                                "name": "耳机",
                                "weburl": "http://redirect.simba.taobao.com/rd?w=unionnojs&f=http%3A%2F%2Fre.taobao.com%2Feauction%3Fe%3Dh5qMOTuIuTzghojqVNxKsT7uB6UAu3F3m7kUtxZzUh2LltG5xFicOSZqewpHPyZz7AXbFc1ykcSNNjMGIU4MqTM%252FQp3P6l3D3%252FpYuRWU7D%252BB3ujUJI0OeA%253D%253D%26ptype%3D100010&k=e2e107a2b72ca1b1&c=un&b=alimm_0&p=mm_42564825_4062167_17418896",
                                "moburl": "http://redirect.simba.taobao.com/rd?w=unionnojs&f=http%3A%2F%2Fre.taobao.com%2Feauction%3Fe%3Dh5qMOTuIuTzghojqVNxKsT7uB6UAu3F3m7kUtxZzUh2LltG5xFicOSZqewpHPyZz7AXbFc1ykcSNNjMGIU4MqTM%252FQp3P6l3D3%252FpYuRWU7D%252BB3ujUJI0OeA%253D%253D%26ptype%3D100010&k=e2e107a2b72ca1b1&c=un&b=alimm_0&p=mm_42564825_4062167_17418896",
                                "logo": "uploads/201402/5301721f405fd.jpg"
                            },
                            {
                                "id": "294",
                                "name": "手机壳",
                                "weburl": "http://redirect.simba.taobao.com/rd?w=unionnojs&f=http%3A%2F%2Fre.taobao.com%2Feauction%3Fe%3D0fUUdGC0fDvebLdhAWchHA1IdSZTjT1hog%252F3K1zSOxCLltG5xFicOSZqewpHPyZz7AXbFc1ykcSNNjMGIU4MqTM%252FQp3P6l3DfoZ6JO9Pop2B3ujUJI0OeA%253D%253D%26ptype%3D100010&k=e2e107a2b72ca1b1&c=un&b=alimm_0&p=mm_42564825_4062167_17422811",
                                "moburl": "http://redirect.simba.taobao.com/rd?w=unionnojs&f=http%3A%2F%2Fre.taobao.com%2Feauction%3Fe%3D0fUUdGC0fDvebLdhAWchHA1IdSZTjT1hog%252F3K1zSOxCLltG5xFicOSZqewpHPyZz7AXbFc1ykcSNNjMGIU4MqTM%252FQp3P6l3DfoZ6JO9Pop2B3ujUJI0OeA%253D%253D%26ptype%3D100010&k=e2e107a2b72ca1b1&c=un&b=alimm_0&p=mm_42564825_4062167_17422811",
                                "logo": "uploads/201402/530173fec5d96.jpg"
                            },
                            {
                                "id": "295",
                                "name": "数据线",
                                "weburl": "http://redirect.simba.taobao.com/rd?w=unionnojs&f=http%3A%2F%2Fre.taobao.com%2Feauction%3Fe%3D9DPESt659ubghojqVNxKsdYfi1ZdE2ADoDkB4aIdoR2LltG5xFicOSZqewpHPyZz7AXbFc1ykcSNNjMGIU4MqTM%252FQp3P6l3D79UVdCzQHJiB3ujUJI0OeA%253D%253D%26ptype%3D100010&k=e2e107a2b72ca1b1&c=un&b=alimm_0&p=mm_42564825_4062167_17426771",
                                "moburl": "http://redirect.simba.taobao.com/rd?w=unionnojs&f=http%3A%2F%2Fre.taobao.com%2Feauction%3Fe%3D9DPESt659ubghojqVNxKsdYfi1ZdE2ADoDkB4aIdoR2LltG5xFicOSZqewpHPyZz7AXbFc1ykcSNNjMGIU4MqTM%252FQp3P6l3D79UVdCzQHJiB3ujUJI0OeA%253D%253D%26ptype%3D100010&k=e2e107a2b72ca1b1&c=un&b=alimm_0&p=mm_42564825_4062167_17426771",
                                "logo": "uploads/201402/530174818d76a.jpg"
                            }
                        ]
                    },
                    "31": {
                        "id": "19",
                        "name": "生活",
                        "data": [
                            {
                                "id": "296",
                                "name": "天气",
                                "weburl": "http://qq.weathercn.com/",
                                "moburl": "http://qq.weathercn.com/",
                                "logo": "uploads/201402/530d898067921.jpg"
                            },
                            {
                                "id": "232",
                                "name": "公交",
                                "weburl": "http://www.8684.cn/",
                                "moburl": "http://m.8684.cn/",
                                "logo": "uploads/201311/527881b70cac8.png"
                            },
                            {
                                "id": "234",
                                "name": "快递",
                                "weburl": "http://www.kuaidi100.com/",
                                "moburl": "http://m.kuaidi100.com/index_all.html ",
                                "logo": "uploads/201311/5278826fca877.png"
                            },
                            {
                                "id": "298",
                                "name": "充值",
                                "weburl": "http://chong.qq.com/",
                                "moburl": "http://chong.qq.com/",
                                "logo": "uploads/201402/530d881932072.jpg"
                            }
                        ]
                    }
                }
            },
            "28": {
                "id": "28",
                "name": "实用工具",
                "data": [
                    {
                        "id": "237",
                        "name": "星座屋",
                        "weburl": "http://www.xingzuowu.com/",
                        "moburl": "http://m.xingzuowu.com/",
                        "logo": "uploads/201311/527883899748e.png"
                    },
                    {
                        "id": "236",
                        "name": "39健康",
                        "weburl": "http://www.39.net/",
                        "moburl": "http://wap.39.net/jbk/index.html ",
                        "logo": "uploads/201311/52788364bcee2.png"
                    },
                    {
                        "id": "233",
                        "name": "老黄历",
                        "weburl": "http://www.laohuangli.net/",
                        "moburl": "http://m.laohuangli.net/",
                        "logo": "uploads/201311/527881dc680a5.png"
                    },
                    {
                        "id": "231",
                        "name": "本地宝",
                        "weburl": "http://www.bendibao.com/",
                        "moburl": "http://m.bendibao.com/touch/",
                        "logo": "uploads/201311/52788195e8324.png"
                    }
                ]
            },
            "29": {
                "id": "29",
                "name": "时尚女性",
                "desp": "",
                "data": {
                    "15": {
                        "id": "3",
                        "name": "女性",
                        "data": [
                            {
                                "id": "17",
                                "name": "美丽说",
                                "weburl": "http://www.meilishuo.com/",
                                "moburl": "http://m.meilishuo.com/",
                                "logo": "uploads/201311/5278962b047eb.png"
                            },
                            {
                                "id": "18",
                                "name": "蘑菇街",
                                "weburl": "http://www.mogujie.com/",
                                "moburl": "http://m.mogujie.com",
                                "logo": "uploads/201311/527895fe78623.png"
                            },
                            {
                                "id": "201",
                                "name": "瑞丽",
                                "weburl": "http://www.rayli.com.cn/",
                                "moburl": "http://wap.rayli.com.cn/",
                                "logo": "uploads/201310/5268c3ce3bd72.png"
                            },
                            {
                                "id": "202",
                                "name": "搜狐女性",
                                "weburl": "http://women.sohu.com/",
                                "moburl": "http://m.sohu.com/c/326/",
                                "logo": "uploads/201310/5268c2fc85c3d.png"
                            }
                        ]
                    }
                }
            },
            "34": {
                "id": "34",
                "name": "软件游戏",
                "desp": "表现出众的手机应用",
                "data": {
                    "9": {
                        "id": "35",
                        "name": "软件",
                        "data": [
                            {
                                "id": "264",
                                "name": "视频",
                                "weburl": "http://v.baidu.com/",
                                "moburl": "http://m.video.baidu.com/",
                                "logo": "uploads/201402/530d8b06ae935.jpg"
                            },
                            {
                                "id": "265",
                                "name": "音乐",
                                "weburl": "http://music.baidu.com/",
                                "moburl": "http://music.baidu.com/",
                                "logo": "uploads/201402/530d8b0064980.jpg"
                            },
                            {
                                "id": "266",
                                "name": "系统",
                                "weburl": "http://www.wandoujia.com/tag/%E7%B3%BB%E7%BB%9F",
                                "moburl": "http://www.wandoujia.com/tag/%E7%B3%BB%E7%BB%9F",
                                "logo": "uploads/201402/530d8af798565.jpg"
                            },
                            {
                                "id": "267",
                                "name": "工具",
                                "weburl": "http://www.wandoujia.com/tag/%E5%B8%B8%E7%94%A8%E5%B7%A5%E5%85%B7",
                                "moburl": "http://www.wandoujia.com/tag/%E5%B8%B8%E7%94%A8%E5%B7%A5%E5%85%B7",
                                "logo": "uploads/201402/530d8aea3216e.jpg"
                            }
                        ]
                    },
                    "11": {
                        "id": "6",
                        "name": "游戏",
                        "data": [
                            {
                                "id": "50",
                                "name": "当乐",
                                "weburl": "http://www.d.cn/",
                                "moburl": "http://x.d.cn/",
                                "logo": "uploads/201311/527885a77ed17.png"
                            },
                            {
                                "id": "49",
                                "name": "17173",
                                "weburl": "http://www.17173.com/",
                                "moburl": "http://m.17173.com/",
                                "logo": "uploads/201311/527885c78e8d4.png"
                            },
                            {
                                "id": "48",
                                "name": "7k7k",
                                "weburl": "http://www.7k7k.com/",
                                "moburl": "http://m.7k7k.com/",
                                "logo": "uploads/201311/527885d353544.png"
                            },
                            {
                                "id": "47",
                                "name": "4399",
                                "weburl": "http://www.4399.com/",
                                "moburl": "http://m.4399.com/",
                                "logo": "uploads/201311/527885e4e6f61.png"
                            }
                        ]
                    },
                    "14": {
                        "id": "36",
                        "name": "精品推荐",
                        "data": [
                            {
                                "id": "268",
                                "name": "地图",
                                "weburl": "http://map.baidu.com/",
                                "moburl": "http://map.baidu.com/mobile/",
                                "logo": "uploads/201402/530d8ad69c908.jpg"
                            },
                            {
                                "id": "269",
                                "name": "来往",
                                "weburl": "http://www.laiwang.com/",
                                "moburl": "http://m.laiwang.com/",
                                "logo": "uploads/201402/530d8acb630fe.jpg"
                            },
                            {
                                "id": "270",
                                "name": "微信",
                                "weburl": "http://weixin.qq.com/",
                                "moburl": "http://weixin.qq.com/",
                                "logo": "uploads/201402/530d8abea28d6.jpg"
                            },
                            {
                                "id": "271",
                                "name": "新闻",
                                "weburl": "http://news.baidu.com/",
                                "moburl": "http://m.baidu.com/news?",
                                "logo": "uploads/201402/530d8ab2a7242.jpg"
                            }
                        ]
                    },
                    "16": {
                        "id": "37",
                        "name": "资源下载",
                        "data": [
                            {
                                "id": "272",
                                "name": "保卫波比",
                                "weburl": "http://www.wandoujia.com/apps/com.qh.tdsld.dj",
                                "moburl": "http://www.wandoujia.com/apps/com.qh.tdsld.dj",
                                "logo": "uploads/201402/52fdbca90f7f1.png"
                            },
                            {
                                "id": "273",
                                "name": "找你妹",
                                "weburl": "http://www.wandoujia.com/apps/com.teayelp.whereareyou ",
                                "moburl": "http://www.wandoujia.com/apps/com.teayelp.whereareyou ",
                                "logo": "uploads/201402/52fdbc912d42d.png"
                            },
                            {
                                "id": "274",
                                "name": "猜图",
                                "weburl": "http://www.wandoujia.com/apps/com.hortor.pictoword",
                                "moburl": "http://www.wandoujia.com/apps/com.hortor.pictoword",
                                "logo": "uploads/201402/52fdbcd9bcd5c.png"
                            },
                            {
                                "id": "275",
                                "name": "水果忍者",
                                "weburl": "http://www.wandoujia.com/apps/com.halfbrick.fruitninja",
                                "moburl": "http://www.wandoujia.com/apps/com.halfbrick.fruitninja",
                                "logo": "uploads/201402/52fdbd01eed48.png"
                            }
                        ]
                    }
                }
            }
        },
        "site_often": [
            {
                "id": "31",
                "sid": "4",
                "name": "1号商城",
                "description": "商城",
                "note": "",
                "weburl": "http://www.1mall.com/3/?tracker_u=106661533",
                "moburl": "http://m.yhd.com/?tracker_u=106661533",
                "add_count": "5700",
                "logo": "uploads/201311/5278887d55b31.png",
                "click_count": "3765",
                "show_is": "Y",
                "sort_order": "4",
                "create_time": "1382496400",
                "start_time": "1383580800",
                "expired_time": "1383667200"
            },
            {
                "id": "144",
                "sid": "16",
                "name": "百度团购",
                "description": "团购",
                "note": "",
                "weburl": "http://tuan.baidu.com/",
                "moburl": "http://mtuan.baidu.com/",
                "add_count": "4294",
                "logo": "uploads/201310/5268ddce84371.png",
                "click_count": "3026",
                "show_is": "Y",
                "sort_order": "4",
                "create_time": "1382496400",
                "start_time": "1383433200",
                "expired_time": "1383519600"
            },
            {
                "id": "19",
                "sid": "4",
                "name": "天猫",
                "description": "商城",
                "note": "",
                "weburl": "http://www.tmall.com/",
                "moburl": "http://m.tmall.com",
                "add_count": "3265",
                "logo": "uploads/201311/527895dd75ffe.png",
                "click_count": "3507",
                "show_is": "Y",
                "sort_order": "4",
                "create_time": "1382496400",
                "start_time": "1383580800",
                "expired_time": "1383667200"
            },
            {
                "id": "18",
                "sid": "3",
                "name": "蘑菇街",
                "description": "女性",
                "note": "",
                "weburl": "http://www.mogujie.com/",
                "moburl": "http://m.mogujie.com",
                "add_count": "5688",
                "logo": "uploads/201311/527895fe78623.png",
                "click_count": "5635",
                "show_is": "Y",
                "sort_order": "4",
                "create_time": "1382496400",
                "start_time": "1383580800",
                "expired_time": "1383667200"
            },
            {
                "id": "94",
                "sid": "12",
                "name": "新浪微博",
                "description": "社交",
                "note": "",
                "weburl": "http://www.weibo.com/",
                "moburl": "http://weibo.cn/pub/",
                "add_count": "4460",
                "logo": "uploads/201310/5268f03f38762.png",
                "click_count": "4571",
                "show_is": "Y",
                "sort_order": "4",
                "create_time": "1382496400",
                "start_time": "1383580800",
                "expired_time": "1383667200"
            },
            {
                "id": "91",
                "sid": "12",
                "name": "腾讯朋友",
                "description": "社交",
                "note": "",
                "weburl": "http://www.pengyou.com/",
                "moburl": "http://m.pengyou.com/",
                "add_count": "5193",
                "logo": "uploads/201310/5269d5f49c89d.png",
                "click_count": "3105",
                "show_is": "Y",
                "sort_order": "4",
                "create_time": "1382496400",
                "start_time": "1383580800",
                "expired_time": "1383667200"
            },
            {
                "id": "35",
                "sid": "5",
                "name": "爱奇艺",
                "description": "视频",
                "note": "",
                "weburl": "http://www.iqiyi.com/",
                "moburl": "http://m.iqiyi.com/",
                "add_count": "4117",
                "logo": "uploads/201311/527887411971f.png",
                "click_count": "4207",
                "show_is": "Y",
                "sort_order": "4",
                "create_time": "1382496400",
                "start_time": "1383667200",
                "expired_time": "1383753600"
            },
            {
                "id": "251",
                "sid": "30",
                "name": "冷笑话精选",
                "description": "",
                "note": "",
                "weburl": "http://m.lengxiaohua.cn/touch/index",
                "moburl": "http://m.lengxiaohua.cn/touch/index",
                "add_count": "3825",
                "logo": "uploads/201311/527c9ac7556ec.png",
                "click_count": "5898",
                "show_is": "Y",
                "sort_order": "4",
                "create_time": "1383897799",
                "start_time": "1383840000",
                "expired_time": "1383926400"
            },
            {
                "id": "241",
                "sid": "32",
                "name": "暴走漫画",
                "description": "",
                "note": "",
                "weburl": "http://m.baozoumanhua.com/",
                "moburl": "http://m.baozoumanhua.com/",
                "add_count": "5418",
                "logo": "uploads/201311/527c98b2e4f42.png",
                "click_count": "3924",
                "show_is": "Y",
                "sort_order": "4",
                "create_time": "1383897266",
                "start_time": "1383840000",
                "expired_time": "1383926400"
            },
            {
                "id": "245",
                "sid": "32",
                "name": "海贼王",
                "description": "",
                "note": "",
                "weburl": "http://mb.ac.qq.com/#!/comic/505430",
                "moburl": "http://mb.ac.qq.com/#!/comic/505430",
                "add_count": "5144",
                "logo": "uploads/201311/527c996843fd2.png",
                "click_count": "4958",
                "show_is": "Y",
                "sort_order": "4",
                "create_time": "1383897448",
                "start_time": "1384099200",
                "expired_time": "1384185600"
            },
            {
                "id": "34",
                "sid": "4",
                "name": "淘宝",
                "description": "商城",
                "note": "",
                "weburl": "http://www.taobao.com/",
                "moburl": "http://m.taobao.com/",
                "add_count": "5636",
                "logo": "uploads/201311/5278876806b5d.png",
                "click_count": "3093",
                "show_is": "Y",
                "sort_order": "9",
                "create_time": "1382496400",
                "start_time": "1383580800",
                "expired_time": "1383667200"
            },
            {
                "id": "26",
                "sid": "4",
                "name": "京东",
                "description": "商城",
                "note": "",
                "weburl": "http://www.jd.com/",
                "moburl": "http://m.jd.com/",
                "add_count": "5539",
                "logo": "uploads/201311/52788dee6791a.png",
                "click_count": "3039",
                "show_is": "Y",
                "sort_order": "12",
                "create_time": "1382496400",
                "start_time": "1383667200",
                "expired_time": "1383753600"
            }
        ],
        "site_tool": [
            {
                "id": "232",
                "sid": "19",
                "name": "公交",
                "description": "8684公交网",
                "note": "",
                "weburl": "http://www.8684.cn/",
                "moburl": "http://m.8684.cn/",
                "add_count": "5850",
                "logo": "uploads/201311/527881b70cac8.png",
                "click_count": "5564",
                "show_is": "Y",
                "sort_order": "1",
                "create_time": "1383629239",
                "start_time": "1383580800",
                "expired_time": "1383667200"
            },
            {
                "id": "234",
                "sid": "19",
                "name": "快递",
                "description": "快递",
                "note": "",
                "weburl": "http://www.kuaidi100.com/",
                "moburl": "http://m.kuaidi100.com/index_all.html ",
                "add_count": "3061",
                "logo": "uploads/201311/5278826fca877.png",
                "click_count": "5086",
                "show_is": "Y",
                "sort_order": "2",
                "create_time": "1383629423",
                "start_time": "1383580800",
                "expired_time": "1383667200"
            },
            {
                "id": "227",
                "sid": "23",
                "name": "有道词典",
                "description": "软件",
                "note": "",
                "weburl": "http://dict.youdao.com/",
                "moburl": "http://cidian.youdao.com/mobile_v4.html?keyfrom=m.youdao.com",
                "add_count": "4647",
                "logo": "uploads/201311/527883b1ba47d.png",
                "click_count": "3887",
                "show_is": "Y",
                "sort_order": "4",
                "create_time": "1383034814",
                "start_time": "1383580800",
                "expired_time": "1383667200"
            },
            {
                "id": "230",
                "sid": "28",
                "name": "中国天气网",
                "description": "天气",
                "note": "",
                "weburl": "http://www.weather.com.cn/",
                "moburl": "http://mobile.weather.com.cn/",
                "add_count": "5343",
                "logo": "uploads/201311/5278815b2fde2.png",
                "click_count": "6049",
                "show_is": "Y",
                "sort_order": "4",
                "create_time": "1383628821",
                "start_time": "1383580800",
                "expired_time": "1383667200"
            }
        ],
        "app_hot": [
            {
                "id": "24",
                "name": "割绳子增强版",
                "adownload": "http://www.adh123.cn/static/soft/割绳子增强版U817wifi联盟.apk",
                "logo": "uploads/201404/535dca60503e4.png",
                "start_time": "1398614400",
                "expired_time": "1430236800"
            },
            {
                "id": "21",
                "name": "来往",
                "adownload": "http://www.adh123.cn/static/soft/laiwang.apk",
                "logo": "uploads/201403/531e9ee7f255e.png",
                "start_time": "1394467200",
                "expired_time": "1451577600"
            },
            {
                "id": "27",
                "name": "熊出没",
                "adownload": "http://www.adh123.cn/static/soft/xiongchumoU812.apk",
                "logo": "uploads/201404/535dea19ecf73.png",
                "start_time": "1398614400",
                "expired_time": "1430236800"
            },
            {
                "id": "25",
                "name": "涂鸦恶魔",
                "adownload": "http://www.adh123.cn/static/soft/涂鸦恶魔-wifi联盟-817.apk",
                "logo": "uploads/201404/535de9bd23a66.png",
                "start_time": "1398614400",
                "expired_time": "1430236800"
            },
            {
                "id": "26",
                "name": "涂鸦上帝",
                "adownload": "http://www.adh123.cn/static/soft/涂鸦上帝-wifi联盟-817.apk",
                "logo": "uploads/201404/535de9ef3c783.png",
                "start_time": "1398614400",
                "expired_time": "1430236800"
            },
            {
                "id": "20",
                "name": "淘宝",
                "adownload": "http://www.adh123.cn/static/soft/taobao.apk",
                "logo": "uploads/201403/531e9e79e3600.png",
                "start_time": "1394467200",
                "expired_time": "1451577600"
            },
            {
                "id": "28",
                "name": "飞机大战豪华版",
                "adownload": "http://www.adh123.cn/static/soft/Forge_V1.1_qyfj14042111_LXTFJ001.apk",
                "logo": "uploads/201404/535dea4c1ae61.png",
                "start_time": "1398614400",
                "expired_time": "1430236800"
            },
            {
                "id": "29",
                "name": "美女野战僵尸",
                "adownload": "http://www.adh123.cn/static/soft/JiangShi_V1.3_qyjs14042106_LXTJS001.apk",
                "logo": "uploads/201404/535dea7c60293.png",
                "start_time": "1398614400",
                "expired_time": "1430236800"
            }
        ]
    }
}